pyaes256_encrypter/__init__.py
pyaes256_encrypter/utils.py
pyaes256_encrypter-1.0.7.dist-info/LICENSE
pyaes256_encrypter-1.0.7.dist-info/WHEEL
pyaes256_encrypter-1.0.7.dist-info/METADATA
pyaes256_encrypter-1.0.7.dist-info/RECORD
