Metadata-Version: 2.1
Name: pyaes256-encrypter
Version: 1.0.7
Summary: A package to simplify the use of AES-256 encryption with random initialization vector.
Home-page: https://github.com/MaiconRenildo/pyaes256_encrypter
License: MIT
Keywords: cryptography,AES256
Author: Maicon Renildo
Author-email: maicon.renildo1@gmail.com
Requires-Python: >=3.6.2,<4.0
Classifier: License :: OSI Approved :: MIT License
Classifier: Programming Language :: Python :: 3
Classifier: Programming Language :: Python :: 3.10
Classifier: Programming Language :: Python :: 3.7
Classifier: Programming Language :: Python :: 3.8
Classifier: Programming Language :: Python :: 3.9
Requires-Dist: cryptography (>=37.0.0)
Project-URL: Documentation, https://github.com/MaiconRenildo/pyaes256_encrypter/blob/master/README.md
